<?xml version="1.0" encoding="utf-8" ?>
<Objects>
  <Storable name="product_stage_log">
    <Execution cod="SEL">
      <Summary>SEL Summary</Summary>
      <Table>product_stage_log</Table>
      <Inputs>
        <Input>id</Input>
        <Input>store_id</Input>
        <Input>log_type_id</Input>
        <Input>log_message</Input>
      </Inputs>
    </Execution>
    <Execution cod="INS">
      <Summary>INS Summary</Summary>
      <Table>product_stage_log</Table>
      <Inputs>
        <Input>store_id</Input>
        <Input>log_type_id</Input>
        <Input>log_message</Input>
      </Inputs>
    </Execution>
    <Execution cod="UPD">
      <Summary>UPD Summary</Summary>
      <Table>product_stage_log</Table>
      <Inputs>
        <Input>id</Input>
        <Input>store_id</Input>
        <Input>log_type_id</Input>
        <Input>log_message</Input>
      </Inputs>
    </Execution>
    <Execution cod="DEL">
      <Summary>DEL Summary</Summary>
      <Table>product_stage_log</Table>
      <Inputs>
        <Input>id</Input>
      </Inputs>
    </Execution>
  </Storable>
</Objects>